dadmatools/__init__.py
dadmatools/normalizer.py
dadmatools/datasets/__init__.py
dadmatools/datasets/base.py
dadmatools/datasets/dataset_utils.py
dadmatools/datasets/datasets_info.py
dadmatools/datasets/datasets/__init__.py
dadmatools/datasets/datasets/Arman/__init__.py
dadmatools/datasets/datasets/Arman/arman.py
dadmatools/datasets/datasets/Arman/info.py
dadmatools/datasets/datasets/FaSpell/__init__.py
dadmatools/datasets/datasets/FaSpell/info.py
dadmatools/datasets/datasets/FaSpell/sp.py
dadmatools/datasets/datasets/FarsTail/__init__.py
dadmatools/datasets/datasets/FarsTail/farstail.py
dadmatools/datasets/datasets/FarsTail/info.py
dadmatools/datasets/datasets/PersianNer/__init__.py
dadmatools/datasets/datasets/PersianNer/info.py
dadmatools/datasets/datasets/PersianNer/persian_ner.py
dadmatools/datasets/datasets/PersianTweets/__init__.py
dadmatools/datasets/datasets/PersianTweets/info.py
dadmatools/datasets/datasets/PersianTweets/persian_tweets.py
dadmatools/datasets/datasets/Peyma/__init__.py
dadmatools/datasets/datasets/Peyma/info.py
dadmatools/datasets/datasets/Peyma/peyma.py
dadmatools/datasets/datasets/TEP/__init__.py
dadmatools/datasets/datasets/TEP/info.py
dadmatools/datasets/datasets/TEP/tep.py
dadmatools/datasets/datasets/Wikipedia/__init__.py
dadmatools/datasets/datasets/Wikipedia/info.py
dadmatools/datasets/datasets/Wikipedia/wikipedia.py
dadmatools/datasets/datasets/persent/__init__.py
dadmatools/datasets/datasets/persent/info.py
dadmatools/datasets/datasets/persent/persent.py
dadmatools/datasets/datasets/persianNews/__init__.py
dadmatools/datasets/datasets/persianNews/info.py
dadmatools/datasets/datasets/persianNews/persian_news.py
dadmatools/datasets/datasets/perudt/__init__.py
dadmatools/datasets/datasets/perudt/info.py
dadmatools/datasets/datasets/perudt/perudt.py
dadmatools/datasets/datasets/pnSummary/__init__.py
dadmatools/datasets/datasets/pnSummary/info.py
dadmatools/datasets/datasets/pnSummary/pn_summary.py
dadmatools-3.0.0.dist-info/LICENSE
dadmatools-3.0.0.dist-info/METADATA
dadmatools-3.0.0.dist-info/WHEEL
dadmatools-3.0.0.dist-info/dependency_links.txt
dadmatools-3.0.0.dist-info/top_level.txt
dadmatools-3.0.0.dist-info/RECORD
