Metadata-Version: 2.1
Name: dadmatools
Version: 3.0.0
Summary: DadmaTools is a Persian NLP toolkit
Home-page: https://github.com/Dadmatech/DadmaTools
Author: Dadmatech AI Company
Author-email: info@dadmatech.ir
License: UNKNOWN
Platform: UNKNOWN
Classifier: Programming Language :: Python :: 3
Classifier: License :: OSI Approved :: Apache Software License 
Classifier: Operating System :: OS Independent
License-File: LICENSE
Requires-Dist: bpemb (>=0.3.3)
Requires-Dist: nltk
Requires-Dist: folium (>=0.2.1)
Requires-Dist: spacy (>=3.0.0)
Requires-Dist: torch (>=1.7.1)
Requires-Dist: transformers (>=4.9.1)
Requires-Dist: h5py (>=3.3.0)
Requires-Dist: Deprecated (==1.2.6)
Requires-Dist: hyperopt (>=0.2.5)
Requires-Dist: pyconll (>=3.1.0)
Requires-Dist: pytorch-transformers (>=1.1.0)
Requires-Dist: segtok (>=1.5.7)
Requires-Dist: tabulate (>=0.8.6)
Requires-Dist: supar (==1.1.2)
Requires-Dist: gensim (>=3.6.0)
Requires-Dist: conllu
Requires-Dist: gdown (>=4.3.1)
Requires-Dist: py7zr (>=0.17.2)
Requires-Dist: html2text
Requires-Dist: tf-estimator-nightly (==2.8.0.dev2021122109)
Requires-Dist: scikit-learn (>=0.24.2)
Requires-Dist: numpy (>=1.24.3)
Requires-Dist: protobuf
Requires-Dist: requests
Requires-Dist: tqdm (>=4.27)
Requires-Dist: langid (==1.1.6)
Requires-Dist: filelock
Requires-Dist: tokenizers (>=0.7.0)
Requires-Dist: regex (!=2019.12.17)
Requires-Dist: packaging
Requires-Dist: sentencepiece
Requires-Dist: sacremoses
Requires-Dist: fasttext
Requires-Dist: hazm
Requires-Dist: kenlm
